Fuckyoubitchbro/__init__.py
Fuckyoubitchbro/main.py
fuckyoubitchbro-0.1.1.dist-info/METADATA
fuckyoubitchbro-0.1.1.dist-info/WHEEL
fuckyoubitchbro-0.1.1.dist-info/entry_points.txt
fuckyoubitchbro-0.1.1.dist-info/top_level.txt
fuckyoubitchbro-0.1.1.dist-info/RECORD
